{"version":"v1","builtAt":"2026-05-20T22:30:49.781Z","signature":"/Users/zacharyellison/code/submarine/src/cockpit.ts:4887:1779316006473.4824|/Users/zacharyellison/code/submarine/src/index.ts:1683:1779316248359.4287|/Users/zacharyellison/code/submarine/src/panel.ts:1129:1779307323959.498|/Users/zacharyellison/code/submarine/src/robot.ts:863:1779307323963.0764|/Users/zacharyellison/code/submarine/vite.config.ts:848:1779307323965.9521","nodes":[["file:/Users/zacharyellison/code/submarine/src/cockpit.ts",{"id":"file:/Users/zacharyellison/code/submarine/src/cockpit.ts","kind":"file","language":"jsts","filePath":"/Users/zacharyellison/code/submarine/src/cockpit.ts","metadata":{"lineCount":175}}],["external:three",{"id":"external:three","kind":"external","language":"jsts","metadata":{"source":"three"}}],["/Users/zacharyellison/code/submarine/src/cockpit.ts:createCockpit",{"id":"/Users/zacharyellison/code/submarine/src/cockpit.ts:createCockpit","kind":"symbol","language":"jsts","filePath":"/Users/zacharyellison/code/submarine/src/cockpit.ts","symbolName":"createCockpit","symbolKind":"function","exported":true,"metadata":{"line":7,"column":1,"cyclomaticComplexity":1,"maxNestingDepth":0,"isBoundaryWrapper":false,"isPassThroughWrapper":false}}],["external:hull.position.set",{"id":"external:hull.position.set","kind":"external","language":"jsts","metadata":{"unresolvedName":"hull.position.set"}}],["external:cockpit.add",{"id":"external:cockpit.add","kind":"external","language":"jsts","metadata":{"unresolvedName":"cockpit.add"}}],["external:dome.position.set",{"id":"external:dome.position.set","kind":"external","language":"jsts","metadata":{"unresolvedName":"dome.position.set"}}],["external:floor.position.set",{"id":"external:floor.position.set","kind":"external","language":"jsts","metadata":{"unresolvedName":"floor.position.set"}}],["external:back.position.set",{"id":"external:back.position.set","kind":"external","language":"jsts","metadata":{"unresolvedName":"back.position.set"}}],["external:panel.position.set",{"id":"external:panel.position.set","kind":"external","language":"jsts","metadata":{"unresolvedName":"panel.position.set"}}],["external:dashGroup.add",{"id":"external:dashGroup.add","kind":"external","language":"jsts","metadata":{"unresolvedName":"dashGroup.add"}}],["external:top.position.set",{"id":"external:top.position.set","kind":"external","language":"jsts","metadata":{"unresolvedName":"top.position.set"}}],["external:colors.forEach",{"id":"external:colors.forEach","kind":"external","language":"jsts","metadata":{"unresolvedName":"colors.forEach"}}],["external:btn.position.set",{"id":"external:btn.position.set","kind":"external","language":"jsts","metadata":{"unresolvedName":"btn.position.set"}}],["external:cushion.position.set",{"id":"external:cushion.position.set","kind":"external","language":"jsts","metadata":{"unresolvedName":"cushion.position.set"}}],["external:backrest.position.set",{"id":"external:backrest.position.set","kind":"external","language":"jsts","metadata":{"unresolvedName":"backrest.position.set"}}],["external:frame.position.set",{"id":"external:frame.position.set","kind":"external","language":"jsts","metadata":{"unresolvedName":"frame.position.set"}}],["external:glass.position.set",{"id":"external:glass.position.set","kind":"external","language":"jsts","metadata":{"unresolvedName":"glass.position.set"}}],["external:tube.position.set",{"id":"external:tube.position.set","kind":"external","language":"jsts","metadata":{"unresolvedName":"tube.position.set"}}],["external:head.position.set",{"id":"external:head.position.set","kind":"external","language":"jsts","metadata":{"unresolvedName":"head.position.set"}}],["external:pWindow.position.set",{"id":"external:pWindow.position.set","kind":"external","language":"jsts","metadata":{"unresolvedName":"pWindow.position.set"}}],["/Users/zacharyellison/code/submarine/src/cockpit.ts:<anonymous>",{"id":"/Users/zacharyellison/code/submarine/src/cockpit.ts:<anonymous>","kind":"symbol","language":"jsts","filePath":"/Users/zacharyellison/code/submarine/src/cockpit.ts","symbolName":"<anonymous>","symbolKind":"function","exported":false,"metadata":{"line":90,"column":18,"cyclomaticComplexity":1,"maxNestingDepth":0,"isBoundaryWrapper":false,"isPassThroughWrapper":false}}],["file:/Users/zacharyellison/code/submarine/src/index.ts",{"id":"file:/Users/zacharyellison/code/submarine/src/index.ts","kind":"file","language":"jsts","filePath":"/Users/zacharyellison/code/submarine/src/index.ts","metadata":{"lineCount":68}}],["external:@iwsdk/core",{"id":"external:@iwsdk/core","kind":"external","language":"jsts","metadata":{"source":"@iwsdk/core"}}],["module:./cockpit.js",{"id":"module:./cockpit.js","kind":"module","language":"jsts","metadata":{"source":"./cockpit.js"}}],["/Users/zacharyellison/code/submarine/src/index.ts:<anonymous>",{"id":"/Users/zacharyellison/code/submarine/src/index.ts:<anonymous>","kind":"symbol","language":"jsts","filePath":"/Users/zacharyellison/code/submarine/src/index.ts","symbolName":"<anonymous>","symbolKind":"function","exported":false,"metadata":{"line":33,"column":9,"cyclomaticComplexity":1,"maxNestingDepth":0,"isBoundaryWrapper":false,"isPassThroughWrapper":false}}],["external:camera.position.set",{"id":"external:camera.position.set","kind":"external","language":"jsts","metadata":{"unresolvedName":"camera.position.set"}}],["symbol-name:createCockpit",{"id":"symbol-name:createCockpit","kind":"symbol","language":"jsts","symbolName":"createCockpit","metadata":{"unresolvedName":"createCockpit"}}],["external:world.createTransformEntity",{"id":"external:world.createTransformEntity","kind":"external","language":"jsts","metadata":{"unresolvedName":"world.createTransformEntity"}}],["external:world.scene.add",{"id":"external:world.scene.add","kind":"external","language":"jsts","metadata":{"unresolvedName":"world.scene.add"}}],["external:sun.position.set",{"id":"external:sun.position.set","kind":"external","language":"jsts","metadata":{"unresolvedName":"sun.position.set"}}],["external:spotlight.position.set",{"id":"external:spotlight.position.set","kind":"external","language":"jsts","metadata":{"unresolvedName":"spotlight.position.set"}}],["external:spotlight.target.position.set",{"id":"external:spotlight.target.position.set","kind":"external","language":"jsts","metadata":{"unresolvedName":"spotlight.target.position.set"}}],["external:glow.position.set",{"id":"external:glow.position.set","kind":"external","language":"jsts","metadata":{"unresolvedName":"glow.position.set"}}],["external:console.log",{"id":"external:console.log","kind":"external","language":"jsts","metadata":{"unresolvedName":"console.log"}}],["file:/Users/zacharyellison/code/submarine/src/panel.ts",{"id":"file:/Users/zacharyellison/code/submarine/src/panel.ts","kind":"file","language":"jsts","filePath":"/Users/zacharyellison/code/submarine/src/panel.ts","metadata":{"lineCount":44}}],["/Users/zacharyellison/code/submarine/src/panel.ts:init",{"id":"/Users/zacharyellison/code/submarine/src/panel.ts:init","kind":"symbol","language":"jsts","filePath":"/Users/zacharyellison/code/submarine/src/panel.ts","symbolName":"init","symbolKind":"function","exported":false,"metadata":{"line":17,"column":3,"cyclomaticComplexity":4,"maxNestingDepth":1,"isBoundaryWrapper":false,"isPassThroughWrapper":false}}],["external:this.queries.welcomePanel.subscribe",{"id":"external:this.queries.welcomePanel.subscribe","kind":"external","language":"jsts","metadata":{"unresolvedName":"this.queries.welcomePanel.subscribe"}}],["external:document.getElementById",{"id":"external:document.getElementById","kind":"external","language":"jsts","metadata":{"unresolvedName":"document.getElementById"}}],["external:xrButton.addEventListener",{"id":"external:xrButton.addEventListener","kind":"external","language":"jsts","metadata":{"unresolvedName":"xrButton.addEventListener"}}],["external:this.world.launchXR",{"id":"external:this.world.launchXR","kind":"external","language":"jsts","metadata":{"unresolvedName":"this.world.launchXR"}}],["external:this.world.exitXR",{"id":"external:this.world.exitXR","kind":"external","language":"jsts","metadata":{"unresolvedName":"this.world.exitXR"}}],["external:this.world.visibilityState.subscribe",{"id":"external:this.world.visibilityState.subscribe","kind":"external","language":"jsts","metadata":{"unresolvedName":"this.world.visibilityState.subscribe"}}],["external:xrButton.setProperties",{"id":"external:xrButton.setProperties","kind":"external","language":"jsts","metadata":{"unresolvedName":"xrButton.setProperties"}}],["/Users/zacharyellison/code/submarine/src/panel.ts:<anonymous>",{"id":"/Users/zacharyellison/code/submarine/src/panel.ts:<anonymous>","kind":"symbol","language":"jsts","filePath":"/Users/zacharyellison/code/submarine/src/panel.ts","symbolName":"<anonymous>","symbolKind":"function","exported":false,"metadata":{"line":34,"column":44,"cyclomaticComplexity":2,"maxNestingDepth":1,"isBoundaryWrapper":false,"isPassThroughWrapper":false}}],["file:/Users/zacharyellison/code/submarine/src/robot.ts",{"id":"file:/Users/zacharyellison/code/submarine/src/robot.ts","kind":"file","language":"jsts","filePath":"/Users/zacharyellison/code/submarine/src/robot.ts","metadata":{"lineCount":36}}],["/Users/zacharyellison/code/submarine/src/robot.ts:init",{"id":"/Users/zacharyellison/code/submarine/src/robot.ts:init","kind":"symbol","language":"jsts","filePath":"/Users/zacharyellison/code/submarine/src/robot.ts","symbolName":"init","symbolKind":"function","exported":false,"metadata":{"line":18,"column":3,"cyclomaticComplexity":1,"maxNestingDepth":0,"isBoundaryWrapper":false,"isPassThroughWrapper":false}}],["external:this.queries.robotClicked.subscribe",{"id":"external:this.queries.robotClicked.subscribe","kind":"external","language":"jsts","metadata":{"unresolvedName":"this.queries.robotClicked.subscribe"}}],["external:AudioUtils.play",{"id":"external:AudioUtils.play","kind":"external","language":"jsts","metadata":{"unresolvedName":"AudioUtils.play"}}],["/Users/zacharyellison/code/submarine/src/robot.ts:<anonymous>",{"id":"/Users/zacharyellison/code/submarine/src/robot.ts:<anonymous>","kind":"symbol","language":"jsts","filePath":"/Users/zacharyellison/code/submarine/src/robot.ts","symbolName":"<anonymous>","symbolKind":"function","exported":false,"metadata":{"line":27,"column":41,"cyclomaticComplexity":1,"maxNestingDepth":0,"isBoundaryWrapper":false,"isPassThroughWrapper":false}}],["/Users/zacharyellison/code/submarine/src/robot.ts:update",{"id":"/Users/zacharyellison/code/submarine/src/robot.ts:update","kind":"symbol","language":"jsts","filePath":"/Users/zacharyellison/code/submarine/src/robot.ts","symbolName":"update","symbolKind":"function","exported":false,"metadata":{"line":26,"column":3,"cyclomaticComplexity":1,"maxNestingDepth":0,"isBoundaryWrapper":false,"isPassThroughWrapper":false}}],["external:this.queries.robot.entities.forEach",{"id":"external:this.queries.robot.entities.forEach","kind":"external","language":"jsts","metadata":{"unresolvedName":"this.queries.robot.entities.forEach"}}],["external:this.player.head.getWorldPosition",{"id":"external:this.player.head.getWorldPosition","kind":"external","language":"jsts","metadata":{"unresolvedName":"this.player.head.getWorldPosition"}}],["external:spinnerObject.getWorldPosition",{"id":"external:spinnerObject.getWorldPosition","kind":"external","language":"jsts","metadata":{"unresolvedName":"spinnerObject.getWorldPosition"}}],["external:spinnerObject.lookAt",{"id":"external:spinnerObject.lookAt","kind":"external","language":"jsts","metadata":{"unresolvedName":"spinnerObject.lookAt"}}],["file:/Users/zacharyellison/code/submarine/vite.config.ts",{"id":"file:/Users/zacharyellison/code/submarine/vite.config.ts","kind":"file","language":"jsts","filePath":"/Users/zacharyellison/code/submarine/vite.config.ts","metadata":{"lineCount":35}}],["external:@iwsdk/vite-plugin-dev",{"id":"external:@iwsdk/vite-plugin-dev","kind":"external","language":"jsts","metadata":{"source":"@iwsdk/vite-plugin-dev"}}],["external:@iwsdk/vite-plugin-uikitml",{"id":"external:@iwsdk/vite-plugin-uikitml","kind":"external","language":"jsts","metadata":{"source":"@iwsdk/vite-plugin-uikitml"}}],["external:vite",{"id":"external:vite","kind":"external","language":"jsts","metadata":{"source":"vite"}}],["external:vite-plugin-mkcert",{"id":"external:vite-plugin-mkcert","kind":"external","language":"jsts","metadata":{"source":"vite-plugin-mkcert"}}]],"edges":[{"from":"file:/Users/zacharyellison/code/submarine/src/cockpit.ts","to":"external:three","kind":"imports"},{"from":"file:/Users/zacharyellison/code/submarine/src/cockpit.ts","to":"/Users/zacharyellison/code/submarine/src/cockpit.ts:createCockpit","kind":"contains"},{"from":"file:/Users/zacharyellison/code/submarine/src/cockpit.ts","to":"/Users/zacharyellison/code/submarine/src/cockpit.ts:createCockpit","kind":"defines"},{"from":"/Users/zacharyellison/code/submarine/src/cockpit.ts:createCockpit","to":"external:hull.position.set","kind":"calls","metadata":{"unresolvedName":"hull.position.set"}},{"from":"/Users/zacharyellison/code/submarine/src/cockpit.ts:createCockpit","to":"external:cockpit.add","kind":"calls","metadata":{"unresolvedName":"cockpit.add"}},{"from":"/Users/zacharyellison/code/submarine/src/cockpit.ts:createCockpit","to":"external:dome.position.set","kind":"calls","metadata":{"unresolvedName":"dome.position.set"}},{"from":"/Users/zacharyellison/code/submarine/src/cockpit.ts:createCockpit","to":"external:floor.position.set","kind":"calls","metadata":{"unresolvedName":"floor.position.set"}},{"from":"/Users/zacharyellison/code/submarine/src/cockpit.ts:createCockpit","to":"external:back.position.set","kind":"calls","metadata":{"unresolvedName":"back.position.set"}},{"from":"/Users/zacharyellison/code/submarine/src/cockpit.ts:createCockpit","to":"external:panel.position.set","kind":"calls","metadata":{"unresolvedName":"panel.position.set"}},{"from":"/Users/zacharyellison/code/submarine/src/cockpit.ts:createCockpit","to":"external:dashGroup.add","kind":"calls","metadata":{"unresolvedName":"dashGroup.add"}},{"from":"/Users/zacharyellison/code/submarine/src/cockpit.ts:createCockpit","to":"external:top.position.set","kind":"calls","metadata":{"unresolvedName":"top.position.set"}},{"from":"/Users/zacharyellison/code/submarine/src/cockpit.ts:createCockpit","to":"external:colors.forEach","kind":"calls","metadata":{"unresolvedName":"colors.forEach"}},{"from":"/Users/zacharyellison/code/submarine/src/cockpit.ts:createCockpit","to":"external:btn.position.set","kind":"calls","metadata":{"unresolvedName":"btn.position.set"}},{"from":"/Users/zacharyellison/code/submarine/src/cockpit.ts:createCockpit","to":"external:cushion.position.set","kind":"calls","metadata":{"unresolvedName":"cushion.position.set"}},{"from":"/Users/zacharyellison/code/submarine/src/cockpit.ts:createCockpit","to":"external:backrest.position.set","kind":"calls","metadata":{"unresolvedName":"backrest.position.set"}},{"from":"/Users/zacharyellison/code/submarine/src/cockpit.ts:createCockpit","to":"external:frame.position.set","kind":"calls","metadata":{"unresolvedName":"frame.position.set"}},{"from":"/Users/zacharyellison/code/submarine/src/cockpit.ts:createCockpit","to":"external:glass.position.set","kind":"calls","metadata":{"unresolvedName":"glass.position.set"}},{"from":"/Users/zacharyellison/code/submarine/src/cockpit.ts:createCockpit","to":"external:tube.position.set","kind":"calls","metadata":{"unresolvedName":"tube.position.set"}},{"from":"/Users/zacharyellison/code/submarine/src/cockpit.ts:createCockpit","to":"external:head.position.set","kind":"calls","metadata":{"unresolvedName":"head.position.set"}},{"from":"/Users/zacharyellison/code/submarine/src/cockpit.ts:createCockpit","to":"external:pWindow.position.set","kind":"calls","metadata":{"unresolvedName":"pWindow.position.set"}},{"from":"file:/Users/zacharyellison/code/submarine/src/cockpit.ts","to":"/Users/zacharyellison/code/submarine/src/cockpit.ts:<anonymous>","kind":"contains"},{"from":"file:/Users/zacharyellison/code/submarine/src/cockpit.ts","to":"/Users/zacharyellison/code/submarine/src/cockpit.ts:<anonymous>","kind":"defines"},{"from":"/Users/zacharyellison/code/submarine/src/cockpit.ts:<anonymous>","to":"external:btn.position.set","kind":"calls","metadata":{"unresolvedName":"btn.position.set"}},{"from":"/Users/zacharyellison/code/submarine/src/cockpit.ts:<anonymous>","to":"external:dashGroup.add","kind":"calls","metadata":{"unresolvedName":"dashGroup.add"}},{"from":"file:/Users/zacharyellison/code/submarine/src/index.ts","to":"external:@iwsdk/core","kind":"imports"},{"from":"file:/Users/zacharyellison/code/submarine/src/index.ts","to":"module:./cockpit.js","kind":"imports"},{"from":"file:/Users/zacharyellison/code/submarine/src/index.ts","to":"external:three","kind":"imports"},{"from":"file:/Users/zacharyellison/code/submarine/src/index.ts","to":"/Users/zacharyellison/code/submarine/src/index.ts:<anonymous>","kind":"contains"},{"from":"file:/Users/zacharyellison/code/submarine/src/index.ts","to":"/Users/zacharyellison/code/submarine/src/index.ts:<anonymous>","kind":"defines"},{"from":"/Users/zacharyellison/code/submarine/src/index.ts:<anonymous>","to":"external:camera.position.set","kind":"calls","metadata":{"unresolvedName":"camera.position.set"}},{"from":"/Users/zacharyellison/code/submarine/src/index.ts:<anonymous>","to":"/Users/zacharyellison/code/submarine/src/cockpit.ts:createCockpit","kind":"calls","metadata":{"unresolvedName":"createCockpit"}},{"from":"/Users/zacharyellison/code/submarine/src/index.ts:<anonymous>","to":"external:world.createTransformEntity","kind":"calls","metadata":{"unresolvedName":"world.createTransformEntity"}},{"from":"/Users/zacharyellison/code/submarine/src/index.ts:<anonymous>","to":"external:world.scene.add","kind":"calls","metadata":{"unresolvedName":"world.scene.add"}},{"from":"/Users/zacharyellison/code/submarine/src/index.ts:<anonymous>","to":"external:sun.position.set","kind":"calls","metadata":{"unresolvedName":"sun.position.set"}},{"from":"/Users/zacharyellison/code/submarine/src/index.ts:<anonymous>","to":"external:spotlight.position.set","kind":"calls","metadata":{"unresolvedName":"spotlight.position.set"}},{"from":"/Users/zacharyellison/code/submarine/src/index.ts:<anonymous>","to":"external:spotlight.target.position.set","kind":"calls","metadata":{"unresolvedName":"spotlight.target.position.set"}},{"from":"/Users/zacharyellison/code/submarine/src/index.ts:<anonymous>","to":"external:glow.position.set","kind":"calls","metadata":{"unresolvedName":"glow.position.set"}},{"from":"/Users/zacharyellison/code/submarine/src/index.ts:<anonymous>","to":"external:console.log","kind":"calls","metadata":{"unresolvedName":"console.log"}},{"from":"file:/Users/zacharyellison/code/submarine/src/panel.ts","to":"external:@iwsdk/core","kind":"imports"},{"from":"file:/Users/zacharyellison/code/submarine/src/panel.ts","to":"/Users/zacharyellison/code/submarine/src/panel.ts:init","kind":"contains"},{"from":"file:/Users/zacharyellison/code/submarine/src/panel.ts","to":"/Users/zacharyellison/code/submarine/src/panel.ts:init","kind":"defines"},{"from":"/Users/zacharyellison/code/submarine/src/panel.ts:init","to":"external:this.queries.welcomePanel.subscribe","kind":"calls","metadata":{"unresolvedName":"this.queries.welcomePanel.subscribe"}},{"from":"/Users/zacharyellison/code/submarine/src/panel.ts:init","to":"external:document.getElementById","kind":"calls","metadata":{"unresolvedName":"document.getElementById"}},{"from":"/Users/zacharyellison/code/submarine/src/panel.ts:init","to":"external:xrButton.addEventListener","kind":"calls","metadata":{"unresolvedName":"xrButton.addEventListener"}},{"from":"/Users/zacharyellison/code/submarine/src/panel.ts:init","to":"external:this.world.launchXR","kind":"calls","metadata":{"unresolvedName":"this.world.launchXR"}},{"from":"/Users/zacharyellison/code/submarine/src/panel.ts:init","to":"external:this.world.exitXR","kind":"calls","metadata":{"unresolvedName":"this.world.exitXR"}},{"from":"/Users/zacharyellison/code/submarine/src/panel.ts:init","to":"external:this.world.visibilityState.subscribe","kind":"calls","metadata":{"unresolvedName":"this.world.visibilityState.subscribe"}},{"from":"/Users/zacharyellison/code/submarine/src/panel.ts:init","to":"external:xrButton.setProperties","kind":"calls","metadata":{"unresolvedName":"xrButton.setProperties"}},{"from":"file:/Users/zacharyellison/code/submarine/src/panel.ts","to":"/Users/zacharyellison/code/submarine/src/panel.ts:<anonymous>","kind":"contains"},{"from":"file:/Users/zacharyellison/code/submarine/src/panel.ts","to":"/Users/zacharyellison/code/submarine/src/panel.ts:<anonymous>","kind":"defines"},{"from":"/Users/zacharyellison/code/submarine/src/panel.ts:<anonymous>","to":"external:document.getElementById","kind":"calls","metadata":{"unresolvedName":"document.getElementById"}},{"from":"/Users/zacharyellison/code/submarine/src/panel.ts:<anonymous>","to":"external:xrButton.addEventListener","kind":"calls","metadata":{"unresolvedName":"xrButton.addEventListener"}},{"from":"/Users/zacharyellison/code/submarine/src/panel.ts:<anonymous>","to":"external:this.world.launchXR","kind":"calls","metadata":{"unresolvedName":"this.world.launchXR"}},{"from":"/Users/zacharyellison/code/submarine/src/panel.ts:<anonymous>","to":"external:this.world.exitXR","kind":"calls","metadata":{"unresolvedName":"this.world.exitXR"}},{"from":"/Users/zacharyellison/code/submarine/src/panel.ts:<anonymous>","to":"external:this.world.visibilityState.subscribe","kind":"calls","metadata":{"unresolvedName":"this.world.visibilityState.subscribe"}},{"from":"/Users/zacharyellison/code/submarine/src/panel.ts:<anonymous>","to":"external:xrButton.setProperties","kind":"calls","metadata":{"unresolvedName":"xrButton.setProperties"}},{"from":"file:/Users/zacharyellison/code/submarine/src/panel.ts","to":"/Users/zacharyellison/code/submarine/src/panel.ts:<anonymous>","kind":"contains"},{"from":"file:/Users/zacharyellison/code/submarine/src/panel.ts","to":"/Users/zacharyellison/code/submarine/src/panel.ts:<anonymous>","kind":"defines"},{"from":"/Users/zacharyellison/code/submarine/src/panel.ts:<anonymous>","to":"external:this.world.launchXR","kind":"calls","metadata":{"unresolvedName":"this.world.launchXR"}},{"from":"/Users/zacharyellison/code/submarine/src/panel.ts:<anonymous>","to":"external:this.world.exitXR","kind":"calls","metadata":{"unresolvedName":"this.world.exitXR"}},{"from":"file:/Users/zacharyellison/code/submarine/src/panel.ts","to":"/Users/zacharyellison/code/submarine/src/panel.ts:<anonymous>","kind":"contains"},{"from":"file:/Users/zacharyellison/code/submarine/src/panel.ts","to":"/Users/zacharyellison/code/submarine/src/panel.ts:<anonymous>","kind":"defines"},{"from":"/Users/zacharyellison/code/submarine/src/panel.ts:<anonymous>","to":"external:xrButton.setProperties","kind":"calls","metadata":{"unresolvedName":"xrButton.setProperties"}},{"from":"file:/Users/zacharyellison/code/submarine/src/robot.ts","to":"external:@iwsdk/core","kind":"imports"},{"from":"file:/Users/zacharyellison/code/submarine/src/robot.ts","to":"/Users/zacharyellison/code/submarine/src/robot.ts:init","kind":"contains"},{"from":"file:/Users/zacharyellison/code/submarine/src/robot.ts","to":"/Users/zacharyellison/code/submarine/src/robot.ts:init","kind":"defines"},{"from":"/Users/zacharyellison/code/submarine/src/robot.ts:init","to":"external:this.queries.robotClicked.subscribe","kind":"calls","metadata":{"unresolvedName":"this.queries.robotClicked.subscribe"}},{"from":"/Users/zacharyellison/code/submarine/src/robot.ts:init","to":"external:AudioUtils.play","kind":"calls","metadata":{"unresolvedName":"AudioUtils.play"}},{"from":"file:/Users/zacharyellison/code/submarine/src/robot.ts","to":"/Users/zacharyellison/code/submarine/src/robot.ts:<anonymous>","kind":"contains"},{"from":"file:/Users/zacharyellison/code/submarine/src/robot.ts","to":"/Users/zacharyellison/code/submarine/src/robot.ts:<anonymous>","kind":"defines"},{"from":"/Users/zacharyellison/code/submarine/src/robot.ts:<anonymous>","to":"external:AudioUtils.play","kind":"calls","metadata":{"unresolvedName":"AudioUtils.play"}},{"from":"file:/Users/zacharyellison/code/submarine/src/robot.ts","to":"/Users/zacharyellison/code/submarine/src/robot.ts:update","kind":"contains"},{"from":"file:/Users/zacharyellison/code/submarine/src/robot.ts","to":"/Users/zacharyellison/code/submarine/src/robot.ts:update","kind":"defines"},{"from":"/Users/zacharyellison/code/submarine/src/robot.ts:update","to":"external:this.queries.robot.entities.forEach","kind":"calls","metadata":{"unresolvedName":"this.queries.robot.entities.forEach"}},{"from":"/Users/zacharyellison/code/submarine/src/robot.ts:update","to":"external:this.player.head.getWorldPosition","kind":"calls","metadata":{"unresolvedName":"this.player.head.getWorldPosition"}},{"from":"/Users/zacharyellison/code/submarine/src/robot.ts:update","to":"external:spinnerObject.getWorldPosition","kind":"calls","metadata":{"unresolvedName":"spinnerObject.getWorldPosition"}},{"from":"/Users/zacharyellison/code/submarine/src/robot.ts:update","to":"external:spinnerObject.lookAt","kind":"calls","metadata":{"unresolvedName":"spinnerObject.lookAt"}},{"from":"file:/Users/zacharyellison/code/submarine/src/robot.ts","to":"/Users/zacharyellison/code/submarine/src/robot.ts:<anonymous>","kind":"contains"},{"from":"file:/Users/zacharyellison/code/submarine/src/robot.ts","to":"/Users/zacharyellison/code/submarine/src/robot.ts:<anonymous>","kind":"defines"},{"from":"/Users/zacharyellison/code/submarine/src/robot.ts:<anonymous>","to":"external:this.player.head.getWorldPosition","kind":"calls","metadata":{"unresolvedName":"this.player.head.getWorldPosition"}},{"from":"/Users/zacharyellison/code/submarine/src/robot.ts:<anonymous>","to":"external:spinnerObject.getWorldPosition","kind":"calls","metadata":{"unresolvedName":"spinnerObject.getWorldPosition"}},{"from":"/Users/zacharyellison/code/submarine/src/robot.ts:<anonymous>","to":"external:spinnerObject.lookAt","kind":"calls","metadata":{"unresolvedName":"spinnerObject.lookAt"}},{"from":"file:/Users/zacharyellison/code/submarine/vite.config.ts","to":"external:@iwsdk/vite-plugin-dev","kind":"imports"},{"from":"file:/Users/zacharyellison/code/submarine/vite.config.ts","to":"external:@iwsdk/vite-plugin-uikitml","kind":"imports"},{"from":"file:/Users/zacharyellison/code/submarine/vite.config.ts","to":"external:vite","kind":"imports"},{"from":"file:/Users/zacharyellison/code/submarine/vite.config.ts","to":"external:vite-plugin-mkcert","kind":"imports"}]}